gpt_invoker.py
myxxxsquared_gpt_invoker-0.2.1.dist-info/licenses/LICENSE
myxxxsquared_gpt_invoker-0.2.1.dist-info/METADATA
myxxxsquared_gpt_invoker-0.2.1.dist-info/WHEEL
myxxxsquared_gpt_invoker-0.2.1.dist-info/top_level.txt
myxxxsquared_gpt_invoker-0.2.1.dist-info/RECORD
