Metadata-Version: 2.4
Name: myxxxsquared-gpt-invoker
Version: 0.2.1
Summary: Thin OpenAI Chat Completions invoker with SQLite caching, usage/cost tracking, and reproducible Markdown dumps.
Author: myxxxsquared
License-Expression: MIT
Project-URL: Homepage, https://github.com/myxxxsquared/myxxxsquared_gpt_invoker
Project-URL: Repository, https://github.com/myxxxsquared/myxxxsquared_gpt_invoker
Project-URL: Issues, https://github.com/myxxxsquared/myxxxsquared_gpt_invoker/issues
Keywords: openai,chat,gpt,invoker,cache,logging
Classifier: Development Status :: 3 - Alpha
Classifier: Intended Audience :: Developers
Classifier: Environment :: Console
Classifier: Operating System :: OS Independent
Classifier: Topic :: Software Development :: Libraries
Classifier: Programming Language :: Python :: 3
Classifier: Programming Language :: Python :: 3 :: Only
Classifier: Programming Language :: Python :: 3.10
Classifier: Programming Language :: Python :: 3.11
Classifier: Programming Language :: Python :: 3.12
Classifier: Programming Language :: Python :: 3.13
Requires-Python: >=3.10
License-File: LICENSE
Requires-Dist: colorlog>=6.4.0
Requires-Dist: openai>=2.0.0
Requires-Dist: python-dotenv>=1.0.0
Provides-Extra: dev
Requires-Dist: pytest>=7.0; extra == "dev"
Requires-Dist: pytest-cov>=4.0; extra == "dev"
Dynamic: license-file
